sta/__init__.py
sta-2.0.1.dist-info/METADATA
sta-2.0.1.dist-info/RECORD
sta-2.0.1.dist-info/WHEEL
sta-2.0.1.dist-info/top_level.txt
